{
  "id": "3a8f67aa-b3f3-4b90-b07f-f0cc4fed6665:multi-system/api-monitor:19",
  "data": {
    "thought": "S19|H|S15|Multi-system Phenotype C4: 'API Compatibility Monitor'. Continuous notebook: (1) Fetches API specs from multiple providers (OpenAPI/GraphQL) (2) Compares against local client code (3) Detects breaking changes, deprecations (4) Generates migration guides. Thoughtbox: reasons about semantic breaking vs. syntactic, prioritizes by usage patterns, drafts PRs. Observable: API diff visualization, impact analysis, migration roadmap. Use case: microservice ecosystems, third-party integrations.",
    "thoughtNumber": 19,
    "totalThoughts": 200,
    "nextThoughtNeeded": true,
    "branchFromThought": 15,
    "branchId": "multi-system/api-monitor",
    "timestamp": "2026-01-17T18:51:13.062Z"
  },
  "prev": "3a8f67aa-b3f3-4b90-b07f-f0cc4fed6665:15",
  "next": [],
  "revisesNode": null,
  "branchOrigin": "3a8f67aa-b3f3-4b90-b07f-f0cc4fed6665:15",
  "branchId": "multi-system/api-monitor"
}